testcontainers/mongodb/__init__.py
tests/test_mongodb.py
testcontainers_mongodb-0.0.1rc1.dist-info/METADATA
testcontainers_mongodb-0.0.1rc1.dist-info/WHEEL
testcontainers_mongodb-0.0.1rc1.dist-info/top_level.txt
testcontainers_mongodb-0.0.1rc1.dist-info/RECORD
